Workbook

Sheet INVERSIONES
B3: INVERSIONES | G3: AÑO 1 | H3: AÑO 2 | I3: AÑO 3 | J3: AÑO 4 | K3: AÑO 5
B4: 1. Gastos de constitución y primer establecimiento
B5: Gastos de constitución | G5: 1500
B6: Gastos de primer establecimiento | G6: 2500
B7: Total de Gastos de constitución y primer establecimiento | G7: =SUM(G5,G6) -> 4000 | H7: =SUM(H5,H6) -> 0 | I7: =SUM(I5,I6) -> 0 | J7: =SUM(J5,J6) -> 0 | K7: =SUM(K5,K6) -> 0
B9: 2. Inmovilizaciones Inmateriales
B10: Aplicaciones informáticas | G10: 2700 | I10: 3600
B11: Total de Inmovilización Inmateriales | G11: =SUM(G10) -> 2700 | H11: =SUM(H10) -> 0 | I11: =SUM(I10) -> 3600 | J11: =SUM(J10) -> 0 | K11: =SUM(K10) -> 0
B13: 3. Inmovilizaciones Materiales
B14: Construcciones | G14: 3000
B15: Maquinaria | G15: 3600
B16: Mobiliario | G16: 3000
B17: Equipos informáticos | G17: 6200 | J17: 5000
B18: Equipos para procesos de prototipado | G18: 18500 | J18: 15000
B19: Elementos de transporte | G19: 9000
B20: Total de Inmovilizaciones Materiales | G20: =SUM(G14:G19) -> 43300 | H20: =SUM(H14:H19) -> 0 | I20: =SUM(I14:I19) -> 0 | J20: =SUM(J14:J19) -> 20000 | K20: =SUM(K14:K19) -> 0
B22: Total de Inversiones | G22: =SUM(G7,G11,G20) -> 50000 | H22: =SUM(H7,H11,H20) -> 0 | I22: =SUM(I7,I11,I20) -> 3600 | J22: =SUM(J7,J11,J20) -> 20000 | K22: =SUM(K7,K11,K20) -> 0

Sheet EVOLUCION INVERSIONES

Sheet INGRESOS
B5: SALUD ESTRUCTURAL Y CONTROL DE EDIFICIOS | G5: Precio medio | H5: Unidades vendidas | I5: Ingresos
B6: Sistemas de detección de presencia y sensores de nivel de agua y temperatura | G6: 2500 | H6: 10 | I6: =PRODUCT(G6,H6) -> 25000
B7: Sensores de vibración e impacto | G7: 2500 | H7: 8 | I7: =PRODUCT(G7,H7) -> 20000
B8: Sistemas de contol de unidades de CC (válvulas de riego, termostatos, sistemas de iluminación, motores, PLC, etc) | G8: 2000 | H8: 12 | I8: =PRODUCT(G8,H8) -> 24000
H9: TOTAL | I9: =SUM(I6,I7,I8) -> 69000
B10: AGRICULTURA DE PRECISIÓN | G10: Precio medio | H10: Unidades vendidos | I10: Ingresos
B11: Sistemas de riego | G11: 500 | H11: 20 | I11: =PRODUCT(G11,H11) -> 10000
B12: Estaciones meteorológicas | G12: 750 | H12: 10 | I12: =PRODUCT(G12,H12) -> 7500
B13: Sistemas de gestión de invernadero | G13: 1000 | H13: 8 | I13: =PRODUCT(G13,H13) -> 8000
B14: Sistemas de detección de crecimiento y diámetro del fruto | G14: 500 | H14: 12 | I14: =PRODUCT(G14,H14) -> 6000
H15: TOTAL | I15: =SUM(I11,I12,I13,I14) -> 31500
B16: CONTROL MEDIOAMBIENTAL | G16: Precio medio | H16: Unidades vendidos | I16: Ingresos
B17: Sistemas de monitorización de la contaminación de la ciudad | G17: 1000 | H17: 12 | I17: =PRODUCT(G17,H17) -> 12000
B18: Sistema de control de emisiones de granjas y criaderos | G18: 1500 | H18: 8 | I18: =PRODUCT(G18,H18) -> 12000
B19: Sistemas de detección de incendios forestales | G19: 1000 | H19: 20 | I19: =PRODUCT(G19,H19) -> 20000
B20: Control de procesos químicos e industriales | G20: 2000 | H20: 10 | I20: =PRODUCT(G20,H20) -> 20000
H21: TOTAL | I21: =SUM(I17,I18,I19,I20) -> 64000
B22: GESTION DE TRÁFICO | G22: Precio medio | H22: Unidades vendidos | I22: Ingresos
B23: Sistema de detección de establecimientos gratuitos al aire libre / cubierto | G23: 10000 | H23: 4 | I23: =PRODUCT(G23,H23) -> 40000
B24: Sistemas de información de estacionamiento disponible | G24: 3000 | H24: 4 | I24: =PRODUCT(G24,H24) -> 12000
H25: TOTAL | I25: =SUM(I23,I24) -> 52000
B26: TOTAL | I26: =SUM(I25,I21,I15,I9) -> 216500
B30: PREVISION DE INGRESOS | E30: AÑO 1 | F30: AÑO 2 | G30: AÑO 3 | H30: AÑO 4 | I30: AÑO 5
B31: SALUD ESTRUCTURAL Y CONTROL DE EDIFCIOS | E31: =I9 -> 69000 | F31: =E31*1.1*1.02 -> 77418 | G31: =F31*1.075*1.02 -> 84888.837 | H31: =G31*1.06*1.02 -> 91781.811 | I31: =H31*1.05*1.02 -> 98298.319
B32: AGRICULTURA DE PRECISIÓN | E32: =I15 -> 31500 | F32: =E32*1.08*1.02 -> 34700.4 | G32: =F32*1.055*1.02 -> 37341.1 | H32: =G32*1.08*1.02 -> 41134.956 | I32: =H32*1.055*1.02 -> 44265.326
B33: CONTROL MEDIOAMBIENTAL | E33: =I21 -> 64000 | F33: =E33*1.1*1.02 -> 71808 | G33: =F33*1.075*1.02 -> 78737.472 | H33: =G33*1.1*1.02 -> 88343.444 | I33: =H33*1.075*1.02 -> 96868.586
B34: GESTION DE TRAFICO | E34: =I25 -> 52000 | F34: =E34*1.1*1.02 -> 58344 | G34: =F34*1.075*1.02 -> 63974.196 | H34: =G34*1.1*1.02 -> 71779.048 | I34: =H34*1.075*1.02 -> 78705.726
B38: PREVISION DE INGRESOS | E38: AÑO 1 | F38: AÑO 2 | G38: AÑO 3 | H38: AÑO 4 | I38: AÑO 5
B39: ESCENARIO 1 (1+4) | E39: =E31+E34 -> 121000 | F39: =F31+F34 -> 135762 | G39: =G31+G34 -> 148863.03 | H39: =H31+H34 -> 163560.86 | I39: =I31+I34 -> 177004.05
B40: ESCENARIO 2 (2+3) | E40: =E32+E33 -> 95500 | F40: =F32+F33 -> 106508.4 | G40: =G32+G33 -> 116078.57 | H40: =H32+H33 -> 129478.4 | I40: =I32+I33 -> 141133.91
B41: ESCENARIO 3 (1+2+3+4) | E41: =SUM(E31:E34) -> 216500 | F41: =SUM(F31:F34) -> 242270.4 | G41: =SUM(G31:G34) -> 264941.61 | H41: =SUM(H31:H34) -> 293039.26 | I41: =SUM(I31:I34) -> 318137.96

Sheet EVOLUCION INGRESOS

Sheet AMORTIZACIONES
B6: Amortizaciones | C6: Año 1 | D6: Año 2 | E6: Año 3 | F6: Año 4 | G6: Año 5
B7: Gastos de constitución | C7: =INVERSIONES!G5*0.2 -> 300 | D7: =INVERSIONES!G5*0.2 -> 300 | E7: =INVERSIONES!G5*0.2 -> 300 | F7: =INVERSIONES!G5*0.2 -> 300 | G7: =INVERSIONES!G5*0.2 -> 300
B8: Gastos de primer establecimiento | C8: =INVERSIONES!G6*0.2 -> 500 | D8: =INVERSIONES!G6*0.2 -> 500 | E8: =INVERSIONES!G6*0.2 -> 500 | F8: =INVERSIONES!G6*0.2 -> 500 | G8: =INVERSIONES!G6*0.2 -> 500
B9: Aplicaciones informáticas | C9: =INVERSIONES!G10*0.5 -> 1350 | D9: =INVERSIONES!G10*0.5 -> 1350 | E9: =INVERSIONES!I10*0.33 -> 1188 | F9: =INVERSIONES!I10*0.33 -> 1188 | G9: =INVERSIONES!I10*0.33 -> 1188
B10: Maquinaria | C10: =INVERSIONES!G15*0.2 -> 720 | D10: =INVERSIONES!G15*0.2 -> 720 | E10: =INVERSIONES!G15*0.2 -> 720 | F10: =INVERSIONES!G15*0.2 -> 720 | G10: =INVERSIONES!G15*0.2 -> 720
B11: Mobiliario | C11: =INVERSIONES!G16*0.2 -> 600 | D11: =INVERSIONES!G16*0.2 -> 600 | E11: =INVERSIONES!G16*0.2 -> 600 | F11: =INVERSIONES!G16*0.2 -> 600 | G11: =INVERSIONES!G16*0.2 -> 600
B12: Equipos informáticos | C12: =INVERSIONES!G17*0.33 -> 2046 | D12: =INVERSIONES!G17*0.33 -> 2046 | E12: =INVERSIONES!G17*0.33 -> 2046 | F12: =INVERSIONES!J17*0.5 -> 2500 | G12: =INVERSIONES!J17*0.5 -> 2500
B13: Equipos para procesos de prototipado | C13: =INVERSIONES!G18*0.33 -> 6105 | D13: =INVERSIONES!G18*0.33 -> 6105 | E13: =INVERSIONES!G18*0.33 -> 6105 | F13: =INVERSIONES!J18*0.5 -> 7500 | G13: =INVERSIONES!J18*0.5 -> 7500
B14: Elementos de transporte | C14: =INVERSIONES!G19*0.2 -> 1800 | D14: =INVERSIONES!G19*0.2 -> 1800 | E14: =INVERSIONES!G19*0.2 -> 1800 | F14: =INVERSIONES!G19*0.2 -> 1800 | G14: =INVERSIONES!G19*0.2 -> 1800
B15: Total | C15: =SUM(C7:C14) -> 13421 | D15: =SUM(D7:D14) -> 13421 | E15: =SUM(E7:E14) -> 13259 | F15: =SUM(F7:F14) -> 15108 | G15: =SUM(G7:G14) -> 15108

Sheet EVOLUCIÓN AMORTIZACIONES

Sheet COSTES VARIABLES
C4: Previsión de costes variables | D4: Año 1 | E4: Año 2 | F4: Año 3 | G4: Año 4 | H4: Año 5
C5: Salud y control de edificios | D5: =INGRESOS!E31*0.25 -> 17250 | E5: =INGRESOS!F31*0.25 -> 19354.5 | F5: =INGRESOS!G31*0.25 -> 21222.209 | G5: =INGRESOS!H31*0.25 -> 22945.453 | H5: =INGRESOS!I31*0.25 -> 24574.58
C6: Agricultura de precisión | D6: =INGRESOS!E32*0.3 -> 9450 | E6: =INGRESOS!F32*0.3 -> 10410.12 | F6: =INGRESOS!G32*0.3 -> 11202.33 | G6: =INGRESOS!H32*0.3 -> 12340.487 | H6: =INGRESOS!I32*0.3 -> 13279.598
C7: Control medioambiental | D7: =INGRESOS!E33*0.25 -> 16000 | E7: =INGRESOS!F33*0.25 -> 17952 | F7: =INGRESOS!G33*0.25 -> 19684.368 | G7: =INGRESOS!H33*0.25 -> 22085.861 | H7: =INGRESOS!I33*0.25 -> 24217.146
C8: Gestión de tráfico | D8: =INGRESOS!E34*0.3 -> 15600 | E8: =INGRESOS!F34*0.3 -> 17503.2 | F8: =INGRESOS!G34*0.3 -> 19192.259 | G8: =INGRESOS!H34*0.3 -> 21533.714 | H8: =INGRESOS!I34*0.3 -> 23611.718

Sheet EVOLUCIÓN COSTES VARIABLES

Sheet COSTES FIJOS
B6: COSTES FIJOS (€) | E6: AÑO 1 | F6: AÑO 2 | G6: AÑO 3 | H6: AÑO 4 | I6: AÑO 5
B7: Gastos de personal | E7: 33537.65 | F7: 36138.98 | G7: 38997.61 | H7: 41648.26 | I7: 44497.62
B8: Alquileres | E8: 6000 | F8: 6240 | G8: 6490 | H8: 6750 | I8: 7020
B9: Gastos generales | E9: 9400 | F9: 10340 | G9: 11374 | H9: 12511 | I9: 13762
B10: Seguros y tributos | E10: 350 | F10: 368 | G10: 386 | H10: 405 | I10: 425
B11: Aprovisionamientos | E11: 6100 | F11: 6405 | G11: 6725 | H11: 7061 | I11: 7414
B12: Otros | E12: 14000 | F12: 1540 | G12: 1694 | H12: 1863 | I12: 2049
B13: Amortizaciones | E13: =AMORTIZACIONES!C15 -> 13421 | F13: =AMORTIZACIONES!D15 -> 13421 | G13: =AMORTIZACIONES!E15 -> 13259 | H13: =AMORTIZACIONES!F15 -> 15108 | I13: =AMORTIZACIONES!G15 -> 15108
B14: TOTAL | E14: =SUM(E7:E13) -> 82808.65 | F14: =SUM(F7:F13) -> 74452.98 | G14: =SUM(G7:G13) -> 78925.61 | H14: =SUM(H7:H13) -> 85346.26 | I14: =SUM(I7:I13) -> 90275.62

Sheet EVOLUCIÓN COSTES FIJOS

Sheet BENEFICIOS
F8: AÑO 1 | G8: AÑO 2 | H8: AÑO 3 | I8: AÑO 4 | J8: AÑO 5
C9: INGRESOS TOTALES
C10: ESCENARIO 1 (1+4) | F10: =INGRESOS!E39 -> 121000 | G10: =INGRESOS!F39 -> 135762 | H10: =INGRESOS!G39 -> 148863.03 | I10: =INGRESOS!H39 -> 163560.86 | J10: =INGRESOS!I39 -> 177004.05
C11: ESCENARIO 2 (2+3) | F11: =INGRESOS!E40 -> 95500 | G11: =INGRESOS!F40 -> 106508.4 | H11: =INGRESOS!G40 -> 116078.57 | I11: =INGRESOS!H40 -> 129478.4 | J11: =INGRESOS!I40 -> 141133.91
C12: ESCENARIO 3 (1+2+3+4) | F12: =INGRESOS!E41 -> 216500 | G12: =INGRESOS!F41 -> 242270.4 | H12: =INGRESOS!G41 -> 264941.61 | I12: =INGRESOS!H41 -> 293039.26 | J12: =INGRESOS!I41 -> 318137.96
C14: COSTES FIJOS | F14: ='COSTES FIJOS'!E14 -> 82808.65 | G14: ='COSTES FIJOS'!F14 -> 74452.98 | H14: ='COSTES FIJOS'!G14 -> 78925.61 | I14: ='COSTES FIJOS'!H14 -> 85346.26 | J14: ='COSTES FIJOS'!I14 -> 90275.62
C15: AMORTIZACIONES | F15: ='COSTES FIJOS'!E13 -> 13421 | G15: ='COSTES FIJOS'!F13 -> 13421 | H15: ='COSTES FIJOS'!G13 -> 13259 | I15: ='COSTES FIJOS'!H13 -> 15108 | J15: ='COSTES FIJOS'!I13 -> 15108
C17: GASTOS VARIABLES
C18: ESCENARIO 1 (1+4) | F18: ='COSTES VARIABLES'!D5+'COSTES VARIABLES'!D8 -> 32850 | G18: ='COSTES VARIABLES'!E5+'COSTES VARIABLES'!E8 -> 36857.7 | H18: ='COSTES VARIABLES'!F5+'COSTES VARIABLES'!F8 -> 40414.468 | I18: ='COSTES VARIABLES'!G5+'COSTES VARIABLES'!G8 -> 44479.167 | J18: ='COSTES VARIABLES'!H5+'COSTES VARIABLES'!H8 -> 48186.298
C19: ESCENARIO 2 (2+3) | F19: ='COSTES VARIABLES'!D6+'COSTES VARIABLES'!D7 -> 25450 | G19: ='COSTES VARIABLES'!E6+'COSTES VARIABLES'!E7 -> 28362.12 | H19: ='COSTES VARIABLES'!F6+'COSTES VARIABLES'!F7 -> 30886.698 | I19: ='COSTES VARIABLES'!G6+'COSTES VARIABLES'!G7 -> 34426.348 | J19: ='COSTES VARIABLES'!H6+'COSTES VARIABLES'!H7 -> 37496.744
C20: ESCENARIO 3 (1+2+3+4) | F20: =SUM('COSTES VARIABLES'!D5:D8) -> 58300 | G20: =SUM('COSTES VARIABLES'!E5:E8) -> 65219.82 | H20: =SUM('COSTES VARIABLES'!F5:F8) -> 71301.166 | I20: =SUM('COSTES VARIABLES'!G5:G8) -> 78905.515 | J20: =SUM('COSTES VARIABLES'!H5:H8) -> 85683.042
C22: BENEFICIOS
C23: ESCENARIO 1 (1+4) | F23: =F10-F14-F18 -> 5341.35 | G23: =G10-G14-G18 -> 24451.32 | H23: =H10-H14-H18 -> 29522.955 | I23: =I10-I14-I18 -> 33735.431 | J23: =J10-J14-J18 -> 38542.128
C24: ESCENARIO 2 (2+3) | F24: =F11-F14-F19 -> -12758.65 | G24: =G11-G14-G19 -> 3693.3 | H24: =H11-H14-H19 -> 6266.2643 | I24: =I11-I14-I19 -> 9705.7921 | J24: =J11-J14-J19 -> 13361.548
C25: ESCENARIO 3 (1+2+3+4) | F25: =F12-F14-F20 -> 75391.35 | G25: =G12-G14-G20 -> 102597.6 | H25: =H12-H14-H20 -> 114714.83 | I25: =I12-I14-I20 -> 128787.48 | J25: =J12-J14-J20 -> 142179.3
C27: IMPUESTOS
C28: ESCENARIO 1 (1+4) | F28: =F23*0.2 -> 1068.27 | G28: =G23*0.2 -> 4890.264 | H28: =H23*0.2 -> 5904.591 | I28: =I23*0.2 -> 6747.0863 | J28: =J23*0.2 -> 7708.4255
C29: ESCENARIO 2 (2+3) | F29: =F24*0.2 -> -2551.73 | G29: =G24*0.2 -> 738.66 | H29: =H24*0.2 -> 1253.2529 | I29: =I24*0.2 -> 1941.1584 | J29: =J24*0.2 -> 2672.3096
C30: ESCENARIO 3 (1+2+3+4) | F30: =F25*0.2 -> 15078.27 | G30: =G25*0.2 -> 20519.52 | H30: =H25*0.2 -> 22942.966 | I30: =I25*0.2 -> 25757.497 | J30: =J25*0.2 -> 28435.859
C32: BENEFICIOS NETOS
C33: ESCENARIO 1 (1+4) | F33: =F23-F28 -> 4273.08 | G33: =G23-G28 -> 19561.056 | H33: =H23-H28 -> 23618.364 | I33: =I23-I28 -> 26988.345 | J33: =J23-J28 -> 30833.702
C34: ESCENARIO 2 (2+3) | F34: =F24-F29 -> -10206.92 | G34: =G24-G29 -> 2954.64 | H34: =H24-H29 -> 5013.0114 | I34: =I24-I29 -> 7764.6336 | J34: =J24-J29 -> 10689.238
C35: ESCENARIO 3 (1+2+3+4) | F35: =F25-F30 -> 60313.08 | G35: =G25-G30 -> 82078.08 | H35: =H25-H30 -> 91771.863 | I35: =I25-I30 -> 103029.99 | J35: =J25-J30 -> 113743.44
C37: BENEFICIOS ACUMULADOS
C38: ESCENARIO 1 (1+4) | F38: =F33 -> 4273.08 | G38: =G33+F38 -> 23834.136 | H38: =H33+G38 -> 47452.5 | I38: =I33+H38 -> 74440.845 | J38: =J33+I38 -> 105274.55
C39: ESCENARIO 2 (2+3) | F39: =F34 -> -10206.92 | G39: =G34+F39 -> -7252.28 | H39: =H34+G39 -> -2239.2686 | I39: =I34+H39 -> 5525.3651 | J39: =J34+I39 -> 16214.603
C40: ESCENARIO 3 (1+2+3+4) | F40: =F35 -> 60313.08 | G40: =G35+F40 -> 142391.16 | H40: =H35+G40 -> 234163.02 | I40: =I35+H40 -> 337193.01 | J40: =J35+I40 -> 450936.45

Sheet EVOLUCIÓN BNA

Sheet CÁLCULO INDICADORES
B4: Proyecto escenario | C4: Inversión inicial (K€) | D4: Flujos netos de caja (FNC) | E4: Inversión inicial (K€) | F4: Flujos netos de caja (FNC) | G4: Inversión inicial (K€) | H4: Flujos netos de caja (FNC) | I4: Inversión inicial (K€) | J4: Flujos netos de caja (FNC) | K4: Inversión inicial (K€) | L4: Flujos netos de caja (FNC)
C5: Año 1 | E5: Año 2 | G5: Año 3 | I5: Año 4 | K5: Año 5
B6: 1+4 | C6: =INVERSIONES!G22 -> 50000 | D6: =BENEFICIOS!F33 -> 4273.08 | E6: 0 | F6: =BENEFICIOS!G33 -> 19561.056 | G6: =INVERSIONES!I22 -> 3600 | H6: =BENEFICIOS!H33 -> 23618.364 | I6: =INVERSIONES!J22 -> 20000 | J6: =BENEFICIOS!I33 -> 26988.345 | K6: 0 | L6: =BENEFICIOS!J33 -> 30833.702
B7: 2+3 | C7: =INVERSIONES!G22 -> 50000 | D7: =BENEFICIOS!F34 -> -10206.92 | E7: 0 | F7: =BENEFICIOS!G34 -> 2954.64 | G7: =INVERSIONES!I22 -> 3600 | H7: =BENEFICIOS!H34 -> 5013.0114 | I7: =INVERSIONES!J22 -> 20000 | J7: =BENEFICIOS!I34 -> 7764.6336 | K7: 0 | L7: =BENEFICIOS!J34 -> 10689.238
B8: 1+2+3+4 | C8: =INVERSIONES!G22 -> 50000 | D8: =BENEFICIOS!F35 -> 60313.08 | E8: 0 | F8: =BENEFICIOS!G35 -> 82078.08 | G8: =INVERSIONES!I22 -> 3600 | H8: =BENEFICIOS!H35 -> 91771.863 | I8: =INVERSIONES!J22 -> 20000 | J8: =BENEFICIOS!I35 -> 103029.99 | K8: 0 | L8: =BENEFICIOS!J35 -> 113743.44
B9: Interés(%) | C9: 0.02 | E9: 0.02 | G9: 0.02 | I9: 0.02 | K9: 0.02
B11: Cálculo del BET (Beneficio acumulado)
B12: Proyecto escenario | C12: último año < 0 | D12: 1er año > 0 | E12: cifra < 0 | F12: cifra > 0 | G12: BET (días) | H12: BET (años) | I12: BET (años + meses)
B13: 1+4
B14: 2+3 | C14: 3 | D14: 4 | E14: =BENEFICIOS!H39 -> -2239.2686 | F14: =BENEFICIOS!I39 -> 5525.3651 | G14: =(-E14*365)/(F14-E14)+C14*365 -> 1200.2636 | H14: =G14/365 -> 3.2883933
B15: 1+2+3+4
B19: Cálculo cifra de equilibrio (Gastos y ingresos acumulados)
B20: Proyecto | C20: último año < 0 | D20: 1er año > 0 | E20: cifra < 0 | F20: cifra > 0 | G20: CE
B21: 1+4 (I) | G21: =(H13-2)*(F21-E21)+E21 -> 0
B22: 1+4 (G)
B23: 2+3 (I) | C23: 3 | D23: 4 | E23: =BENEFICIOS!F11+BENEFICIOS!G11+BENEFICIOS!H11 -> 318086.97 | F23: =E23+BENEFICIOS!I11 -> 447565.37 | G23: =(H14-C23)*(F23-E23)+E23 -> 355427.68
B24: 2+3 (G) | C24: 3 | D24: 4 | E24: =BENEFICIOS!F14+BENEFICIOS!F19+BENEFICIOS!G14+BENEFICIOS!G19+BENEFICIOS!H14+BENEFICIOS!H19 -> 320886.06 | F24: =BENEFICIOS!I14+BENEFICIOS!I19+E24 -> 440658.67 | G24: =(H14-C24)*(F24-E24)+E24 -> 355427.68
B25: 1+2+3+4 (I)
B26: 1+2+3+4 (G)
B29: Escenarios | C29: VAN | D29: BET | E29: ROI | F29: CE | G29: RI
B30: 1+2 | C30: =-C6+D6/(1+C9)-E6+F6/(1+E9)^2-G6+H6/(1+G9)^3-I6+J6/(1+I9)^4-K6+L6/(1+K9)^5 -> 24506.976 | E30: =BENEFICIOS!J38 -> 105274.55 | G30: =(BENEFICIOS!J38-INVERSIONES!G22-INVERSIONES!I22-INVERSIONES!J22)/(INVERSIONES!G22+INVERSIONES!I22+INVERSIONES!J22) -> 0.4303607
B31: 3+4 | C31: =-C7+D7/(1+C9)-E7+F7/(1+E9)^2-G7+H7/(1+G9)^3-I7+J7/(1+I9)^4-K7+L7/(1+K9)^5 -> -59188.11 | D31: =H14 -> 3.2883933 | E31: =BENEFICIOS!J39 -> 16214.603 | F31: =G23 -> 355427.68 | G31: =(BENEFICIOS!J39-INVERSIONES!G22-INVERSIONES!I22-INVERSIONES!J22)/(INVERSIONES!G22+INVERSIONES!I22+INVERSIONES!J22) -> -0.77969289
B32: 1+2+3+4 | C32: =-C8+D8/(1+C9)-E8+F8/(1+E9)^2-G8+H8/(1+G9)^3-I8+J8/(1+I9)^4-K8+L8/(1+K9)^5 -> 349104.75 | E32: =BENEFICIOS!J40 -> 450936.45 | G32: =(BENEFICIOS!J40-INVERSIONES!G22-INVERSIONES!I22-INVERSIONES!J22)/(INVERSIONES!G22+INVERSIONES!I22+INVERSIONES!J22) -> 5.1268539
